mathml2omml/__init__.py
mathml2omml/op_dict.py
mathml2omml-0.0.2.dist-info/LICENSE
mathml2omml-0.0.2.dist-info/METADATA
mathml2omml-0.0.2.dist-info/WHEEL
mathml2omml-0.0.2.dist-info/top_level.txt
mathml2omml-0.0.2.dist-info/RECORD
