Metadata-Version: 1.2
Name: mathml2omml
Version: 0.0.2
Summary: UNKNOWN
Home-page: https://github.com/amedama41/mathml2omml
Author: amedama41
Author-email: kamo.devel41@gmail.com
License: UNKNOWN
Keywords: MathML,OpenXML
Platform: UNKNOWN
Classifier: License :: OSI Approved :: MIT License
Classifier: Programming Language :: Python :: 3
Classifier: Topic :: Text Processing :: Markup :: XML
Requires-Python: >=3.5
